automlstreams/__init__.py
automlstreams/console.py
automlstreams/evaluators/__init__.py
automlstreams/evaluators/evaluate_pretrained.py
automlstreams/meta/__init__.py
automlstreams/meta/last_best_classifier.py
automlstreams/meta/meta_classifier.py
automlstreams/streams/__init__.py
automlstreams/streams/kafka_stream.py
automl_streams-0.0.2.dist-info/AUTHORS.md
automl_streams-0.0.2.dist-info/LICENSE
automl_streams-0.0.2.dist-info/METADATA
automl_streams-0.0.2.dist-info/WHEEL
automl_streams-0.0.2.dist-info/top_level.txt
automl_streams-0.0.2.dist-info/RECORD
