Metadata-Version: 2.1
Name: automl-streams
Version: 0.0.2
Summary: AutoML framework for implementing automated machine learning on data streams.
Home-page: https://github.com/AlexImb/automl-streams
Author: Alexandru-Ionut Imbrea
Author-email: aleximbrea@gmail.com
License: mit
Project-URL: Documentation, https://github.com/AlexImb/automl-streams
Platform: any
Classifier: Development Status :: 2 - Pre-Alpha
Classifier: Programming Language :: Python
Classifier: Operating System :: OS Independent
Requires-Python: >=3.6
Requires-Dist: scikit-learn (>=0.22.1)
Requires-Dist: scikit-multiflow (>=0.4.1)
Requires-Dist: kafka-python (>=1.4.7)
Requires-Dist: pymfe (>=0.2.0)
Provides-Extra: docs
Requires-Dist: sphinx ; extra == 'docs'
Provides-Extra: testing
Requires-Dist: pytest ; extra == 'testing'
Requires-Dist: pytest-cov ; extra == 'testing'
